Jasper-0.1.dist-info/DESCRIPTION.rst
Jasper-0.1.dist-info/METADATA
Jasper-0.1.dist-info/RECORD
Jasper-0.1.dist-info/WHEEL
Jasper-0.1.dist-info/entry_points.txt
Jasper-0.1.dist-info/metadata.json
Jasper-0.1.dist-info/top_level.txt
jasper/__init__.py
jasper/context.py
jasper/display.py
jasper/entrypoints.py
jasper/exceptions.py
jasper/expect.py
jasper/feature.py
jasper/runner.py
jasper/scenario.py
jasper/steps.py
jasper/suite.py
jasper/utility.py
