Metadata-Version: 2.0
Name: Jasper
Version: 0.1
Summary: An asynchronous behavior-driven development framework
Home-page: https://github.com/tylerlaberge/Jasper
Author: Tyler LaBerge
Author-email: tyler.laberge@maine.edu
License: MIT
Keywords: python async asynchronous test test-driven-development behavior behavior-driven-development tdd bdd testing test-automation test-framework testing-tools tests framework library
Platform: UNKNOWN
Requires-Dist: click (==6.7)
Requires-Dist: colorama (==0.3.7)
Requires-Dist: termcolor (==1.1.0)
Requires-Dist: tqdm (==4.11.2)
